glcm_cupy/__init__.py
glcm_cupy/conf.py
glcm_cupy/cross/__init__.py
glcm_cupy/cross/glcm_cross.py
glcm_cupy/cross/glcm_cross_py.py
glcm_cupy/glcm/__init__.py
glcm_cupy/glcm/glcm.py
glcm_cupy/glcm/glcm_py.py
glcm_cupy/glcm_base.py
glcm_cupy/glcm_py_base.py
glcm_cupy/kernel.py
glcm_cupy/utils.py
glcm_cupy-0.2.1.dist-info/METADATA
glcm_cupy-0.2.1.dist-info/WHEEL
glcm_cupy-0.2.1.dist-info/RECORD
