Metadata-Version: 2.1
Name: glcm_cupy
Version: 0.2.1
Summary: Binned GLCM 5 Features implemented in CuPy
Home-page: https://github.com/Eve-ning/glcmbin5_cupy
License: MIT
Author: Evening
Requires-Python: >=3.9
Classifier: Development Status :: 4 - Beta
Classifier: Environment :: GPU :: NVIDIA CUDA
Classifier: License :: OSI Approved :: MIT License
Classifier: Operating System :: OS Independent
Classifier: Programming Language :: Python :: 3
Classifier: Programming Language :: Python :: 3.9
Classifier: Programming Language :: Python :: 3.10
Classifier: Programming Language :: Python :: 3.11
Classifier: Topic :: Scientific/Engineering :: Artificial Intelligence
Classifier: Topic :: Scientific/Engineering :: Image Processing
Classifier: Topic :: Scientific/Engineering :: Image Recognition
Requires-Dist: scikit-image (>=0.22.0,<0.23.0)
Requires-Dist: tqdm (>=4.66.1,<5.0.0)
Project-URL: Repository, https://github.com/Eve-ning/glcmbin5_cupy
